CHANGES.txt
LICENSE.txt
MANIFEST.in
README.md
README.txt
TODO.sh
runtests.sh
setup.py
ModelicaRes.egg-info/PKG-INFO
ModelicaRes.egg-info/SOURCES.txt
ModelicaRes.egg-info/dependency_links.txt
ModelicaRes.egg-info/requires.txt
ModelicaRes.egg-info/top_level.txt
ModelicaRes.egg-info/zip-safe
bin/loadres
doc/.modelica.pws
doc/.modelicares.pws
doc/README.md
doc/changelog.rst
doc/changes.rst
doc/conf.py
doc/credits.rst
doc/exps.doe.rst
doc/exps.rst
doc/index.rst
doc/license.rst
doc/linres.rst
doc/loadres.rst
doc/make.py
doc/modelicares.exps.doe.rst
doc/modelicares.exps.rst
doc/modelicares.linres.rst
doc/modelicares.rst
doc/modelicares.simres.rst
doc/modelicares.texunit.rst
doc/modelicares.util.rst
doc/modules-scripts.rst
doc/simres.rst
doc/texunit.rst
doc/util.rst
doc/_static/ChuaCircuit-small.png
doc/_static/ChuaCircuit.png
doc/_static/PIDs-bode-small.png
doc/_static/PIDs-bode.png
doc/_static/ThreeTanks-small.png
doc/_static/ThreeTanks.png
doc/_static/analytics.js
doc/_static/browse.png
doc/_static/copybutton.js
doc/_static/custom.css
doc/_static/favicon.ico
doc/_static/full-size.png
doc/_static/hspace.png
doc/_static/logo.gif
doc/_static/logo.png
doc/_templates/download.html
doc/_templates/globaltoc.html
doc/_templates/info.html
doc/_templates/layout.html
doc/_templates/links.html
doc/_templates/search.html
doc/_templates/searchbox.html
doc/_templates/source.html
doc/extra/googledadb6c37b51fb2dc.html
examples/ChuaCircuit.mat
examples/ChuaCircuit.py
examples/ChuaCircuits.py
examples/PID-bode.py
examples/PID-nyquist.py
examples/PID.mat
examples/PIDs-bode.py
examples/PIDs-nyquist.py
examples/README.md
examples/ThreeTanks.mat
examples/ThreeTanks.py
examples/advanced.ipynb
examples/dsin.txt
examples/load-csv.csv
examples/load-csv.py
examples/matplotlibrc
examples/tutorial.ipynb
examples/util-ArrowLine.py
examples/util-add_arrows.py
examples/util-add_hlines.py
examples/util-add_vlines.py
examples/util-quiver.py
examples/util-setup_subplots.py
examples/util-shift_scale_x.py
examples/util-shift_scale_y.py
examples/ChuaCircuit/README.md
examples/ChuaCircuit/sim_and_plot.py
examples/ChuaCircuit/1/dsres.mat
examples/ChuaCircuit/2/dsres.mat
examples/PID/README.md
