Metadata-Version: 1.1
Name: ModelicaRes
Version: 0.12.2
Summary: Utilities to set up and analyze Modelica simulation experiments
Home-page: http://kdavies4.github.io/ModelicaRes/
Author: Kevin Davies
Author-email: kdavies4@gmail.com
License: BSD-compatible (see LICENSE.txt)
Download-URL: https://github.com/kdavies4/ModelicaRes/archive/v0.12.2.zip
Keywords: Modelica,plot,results,simulation,experiment,Dymola,matplotlib,pandas
Platform: any
Classifier: Development Status :: 4 - Beta
Classifier: Operating System :: POSIX :: Linux
Classifier: Operating System :: Microsoft :: Windows
Classifier: Environment :: Console
Classifier: License :: OSI Approved :: BSD License
Classifier: Programming Language :: Python :: 2.7
Classifier: Programming Language :: Python :: 3.2
Classifier: Programming Language :: Python :: 3.3
Classifier: Programming Language :: Python :: 3.4
Classifier: Intended Audience :: Science/Research
Classifier: Topic :: Scientific/Engineering
Classifier: Topic :: Utilities
Requires: numpy
Requires: scipy (>=0.10.0)
Requires: matplotlib (>=1.3.1)
Requires: pandas
Requires: control
Requires: six
Provides: modelicares
